{
    "name": "Product",
    "fields": [
        {
            "fieldName": "name",
            "fieldType": "String",
            "fieldValidateRules": [
                "required"
            ]
        },
        {
            "fieldName": "description",
            "fieldType": "String"
        },
        {
            "fieldName": "packaging",
            "fieldType": "Double",
            "fieldValidateRules": [
                "required"
            ]
        },
        {
            "fieldName": "packagingUnit",
            "fieldType": "Unit",
            "fieldValues": "ML,KG,M"
        },
        {
            "fieldName": "link",
            "fieldType": "String"
        },
        {
            "fieldName": "price",
            "fieldType": "Double"
        },
        {
            "fieldName": "reference",
            "fieldType": "String"
        }
    ],
    "relationships": [
        {
            "relationshipName": "shop",
            "otherEntityName": "shop",
            "relationshipType": "many-to-one",
            "otherEntityField": "id"
        }
    ],
    "changelogDate": "20190126160419",
    "entityTableName": "product",
    "dto": "mapstruct",
    "pagination": "pagination",
    "service": "serviceImpl",
    "jpaMetamodelFiltering": false,
    "fluentMethods": true,
    "clientRootFolder": "",
    "applications": "*",
    "angularJSSuffix": "ctm"
}